dask_geopandas/__init__.py
dask_geopandas/_expr.py
dask_geopandas/_version.py
dask_geopandas/backends.py
dask_geopandas/clip.py
dask_geopandas/core.py
dask_geopandas/expr.py
dask_geopandas/geohash.py
dask_geopandas/hilbert_distance.py
dask_geopandas/morton_distance.py
dask_geopandas/sjoin.py
dask_geopandas/io/__init__.py
dask_geopandas/io/arrow.py
dask_geopandas/io/file.py
dask_geopandas/io/parquet.py
dask_geopandas/tests/__init__.py
dask_geopandas/tests/conftest.py
dask_geopandas/tests/test_clip.py
dask_geopandas/tests/test_core.py
dask_geopandas/tests/test_distributed.py
dask_geopandas/tests/test_geohash.py
dask_geopandas/tests/test_hilbert_distance.py
dask_geopandas/tests/test_morton_distance.py
dask_geopandas/tests/test_sjoin.py
dask_geopandas/tests/test_spatial_partitioning.py
dask_geopandas/tests/io/__init__.py
dask_geopandas/tests/io/conftest.py
dask_geopandas/tests/io/test_arrow.py
dask_geopandas/tests/io/test_backend_integration.py
dask_geopandas/tests/io/test_file.py
dask_geopandas/tests/io/test_parquet.py
dask_geopandas-0.5.0.dist-info/licenses/LICENSE
dask_geopandas-0.5.0.dist-info/METADATA
dask_geopandas-0.5.0.dist-info/WHEEL
dask_geopandas-0.5.0.dist-info/top_level.txt
dask_geopandas-0.5.0.dist-info/RECORD
