Metadata-Version: 2.4
Name: dask-geopandas
Version: 0.5.0
Summary: Parallel GeoPandas with Dask
Author-email: Julia Signell <jsignell@gmail.com>
Maintainer: GeoPandas contributors
License: BSD 3-Clause
Project-URL: Home, https://geopandas.org
Project-URL: Documentation, https://dask-geopandas.readthedocs.io/
Project-URL: Repository, https://github.com/geopandas/dask-geopandas
Project-URL: Issue Tracker, https://github.com/geopandas/dask-geopandas/issues
Keywords: dask,geopandas,spatial,distributed,cluster
Classifier: Development Status :: 5 - Production/Stable
Classifier: Intended Audience :: Developers
Classifier: Intended Audience :: Science/Research
Classifier: License :: OSI Approved :: BSD License
Classifier: Operating System :: OS Independent
Classifier: Programming Language :: Python :: 3
Classifier: Programming Language :: Python :: 3 :: Only
Classifier: Topic :: Scientific/Engineering
Classifier: Topic :: Scientific/Engineering :: GIS
Classifier: Topic :: System :: Distributed Computing
Requires-Python: >=3.10
License-File: LICENSE
Requires-Dist: geopandas>=0.14.3
Requires-Dist: shapely>=2.0
Requires-Dist: dask[dataframe]>=2025.1.0
Requires-Dist: packaging
Provides-Extra: test
Requires-Dist: pytest; extra == "test"
Dynamic: license-file
